[
  {
    "id": "recognition-matsuri-1750933688903",
    "organizer": "",
    "price": "",
    "description": "成田山新勝寺のご本尊である不動明王の本地仏、奥之院大日如来を供養する祭礼の「成田山祇園会」にあわせて、周辺の町内が一体となり、夏祭りとして「成田祇園祭」が開催されます。新勝寺で執り行われる「成田山祇園会」は約300年の歴史があり、大日如来に五穀豊穣や万民豊楽などが祈願され、大日如来が祀られた奥之院が特別開帳されます。市内一帯では、豪華絢爛な御輿と10台の山車や屋台が3日間にわたり引き回され、踊りとお囃子の競演が披露されます。例年40万人を超える見物客が集まります。",
    "themeColor": "red",
    "detailLink": "/chiba/matsuri/activity-33688903",
    "title": "成田祇園祭（なりたぎおんさい）",
    "location": "〒286-0023　千葉県成田市成田1",
    "date": "2025年7月4日～6日",
    "image": "https://upload.wikimedia.org/wikipedia/commons/thumb/6/63/Narita-gion-festival-1%2CNarita-city%2CJapan.jpg/2880px-Narita-gion-festival-1%2CNarita-city%2CJapan.jpg",
    "likes": 0
  }
]