{
  "id": "1751107828174",
  "name": "第73回 小山の花火",
  "address": "JR小山駅西口",
  "datetime": "2025年9月23日(祝) 18:30～",
  "venue": "観晃橋下流　思川河畔",
  "access": "【電車】JR小山駅西口から徒歩8分MAP",
  "organizer": "",
  "price": "あり\nテーブルイス席6名30000円～25200円、プレミアムリクライニング席2名15000円、ベンチ席2名8000円、芝生席4名5000円、ペア階段席・北エリア:2名6000円、北エリア:1名3000円、階段席中央・南エリア:1名3500円、市庁舎内4～6階西側廊下席1名10000円、カメラマン席2名8000円、第2駐車場内丸テーブルイス席4名22000円、城山公園内丸テーブルイス席4名20000円、城山公園内芝生席1名1000円※問い合わせ先は小山の花火有料席センター070-2294-8036",
  "contact": "0285-22-9273 おやまサマーフェスティバル2024実行委員会",
  "website": "https://www.oyamanohanabi.com/",
  "googleMap": "https://www.google.com/maps/embed/v1/place?key=AIzaSyDbSCIe9u9tyzmG1OdAae8eRLPGmK5sevc&zoom=16&q=36.316432,139.796341&center=36.316432,139.796341",
  "region": "kitakanto",
  "description": "【※大会プログラムは過去の情報になります。開催予定の大会については詳細が決定次第、情報を更新します】栃木県小山市の清流思川を会場に開催される、関東有数の規模を誇る大会。市制70周年の今年は、おやまサマーフェスティバル2024「天に願いを 希望の花火！～make history～」をテーマに様々な花火が打ち上げられる。会場には有料席が設けられ迫力満点の花火が堪能できる。",
  "activityType": "hanabi",
  "detailLink": "/kitakanto/hanabi/activity-73-07828173",
  "themeColor": "red",
  "status": "scheduled",
  "media": [
    {
      "type": "image",
      "url": "https://cdn.midjourney.com/f9e41f52-d573-4abd-a8ca-dbb0fc4beb37/0_3.png",
      "title": "第73回 小山の花火图片1",
      "alt": "第73回 小山の花火图片1",
      "caption": ""
    }
  ],
  "createdAt": "2025-06-28T10:50:28.181Z",
  "updatedAt": "2025-06-28T10:50:28.181Z"
}