{
  "id": "recognition-hanabi-1750948520819",
  "name": "松戸花火大会2025",
  "fireworksCount": "1万発",
  "fireworksTime": "70分",
  "expectedVisitors": "約27万人　2024年実績",
  "date": "2025年8月2日(土)",
  "time": "19:15～20:20",
  "venue": "古ヶ崎河川敷スポーツ広場",
  "access": "【電車】JR松戸駅または北松戸駅から徒歩35分 ※徒歩での来場をお願いしていますMAP",
  "weatherInfo": "荒天時は中止、延期なし",
  "parking": "×",
  "price": "あり\n席の販売開始は6月中旬を予定。公式サイト参照",
  "contact": "047-366-7327 松戸市文化スポーツ部文化にぎわい創造課",
  "foodStalls": "あり",
  "notes": "详见官网",
  "website": "https://matsudo-hanabi.com/",
  "googleMap": "https://www.google.com/maps/embed/v1/place?key=AIzaSyDbSCIe9u9tyzmG1OdAae8eRLPGmK5sevc&zoom=16&q=35.803223,139.892193&center=35.803223,139.892193",
  "description": "千葉県松戸市で開催される花火大会。打ち上げ場所の古ヶ崎河川敷スポーツ広場では、会場内に観覧席が設けられており迫力満点の花火を満喫できる。なお、会場内への入場は有料観覧席チケットが必要となり、販売は6月中旬を予定している。また、会場内にキッチンカーも設置予定で、グルメも楽しめる。",
  "highlights": "観覧場所の広さと開放感に加え、約1万発にもおよぶ多彩な花火の競演が見どころ。スターマイン、各種仕掛け花火などのプログラムが予定されている。",
  "region": "chiba",
  "activityType": "hanabi",
  "detailLink": "/chiba/hanabi/activity-event-2025-48520819",
  "themeColor": "red",
  "status": "scheduled",
  "media": [
    {
      "type": "image",
      "url": "https://machitto.jp/wp-content/uploads/2025/05/IMG_2460-854x475.jpeg",
      "title": "松戸花火大会2025图片1",
      "alt": "松戸花火大会2025图片1",
      "caption": ""
    }
  ],
  "createdAt": "2025-06-29T04:41:09.569Z",
  "updatedAt": "2025-06-29T04:41:09.569Z"
}