[
  {
    "id": "recognition-hanami-1750933861522",
    "organizer": "",
    "website": "",
    "description": "明月院のアジサイの開催期間：2025年6月上旬～下旬。じゃらんnetでは明月院のアジサイへの口コミや投稿写真をご紹介。明月院のアジサイへのアクセス情報や混雑状況などもご確認頂けます。明月院のアジサイ周辺のホテル/観光スポット/ご当地グルメ/事件情報も充実。",
    "themeColor": "red",
    "detailLink": "/kanagawa/hanami/activity-33861522",
    "title": "明月院的绣球花（めいげついんのアジサイ）",
    "location": "〒247-0062　神奈川県鎌倉市山ノ内189",
    "date": "2025年6月上旬～下旬　 期間中の拝観時間/8:30～受付終了16:30（閉門17:00）",
    "image": "https://hanamap.com/media/002/202203/%E6%98%8E%E6%9C%88%E9%99%A2.jpg",
    "likes": 94
  },
  {
    "id": "recognition-hanami-1750948812517",
    "title": "长谷寺（长谷观音）的绣球花（はせでら　はせかんのん　のアジサイ）",
    "description": "長谷寺（長谷観音）のアジサイの開催期間：2025年5月下旬～7月上旬。じゃらんnetでは長谷寺（長谷観音）のアジサイへの口コミや投稿写真をご紹介。長谷寺（長谷観音）のアジサイへのアクセス情報や混雑状況などもご確認頂けます。長谷寺（長谷観音）のアジサイ周辺のホテル/観光スポット/ご当地グルメ/事件情報も充実。",
    "location": "〒248-0016　神奈川県鎌倉市長谷3-11-2",
    "date": "2025年5月下旬～7月上旬　 拝観時間/8:00～17:00（閉山17:30）　※あじさい路でのアジサイ鑑賞/五分咲き～見頃が終わるまで、あじさい入場券（有料）を領布。詳細はホームページをご確認ください。",
    "image": "https://sumahononakani.com/tjn/upload/img_reports/detail/2c449678d08eef57a2e8a9cd0011ef07ba5e745739bf5dcbb54a9185a472b0ea645b287a8105a.jpg",
    "detailLink": "/kanagawa/hanami/activity-48812517",
    "likes": 63,
    "themeColor": "red"
  }
]